unitprompt/__init__.py
unitprompt/llm.py
unitprompt/matchers/parsable/__init__.py
unitprompt/matchers/parsable/test_parsable_csv.py
unitprompt/matchers/parsable/test_parsable_json.py
unitprompt/matchers/parsable/test_parsable_xml.py
unitprompt/matchers/parsable/test_parsable_yaml.py
unitprompt/matchers/style/__init__.py
unitprompt/matchers/style/test_conciseness.py
unitprompt/matchers/test_fulfills.py
unitprompt/matchers/uses/__init__.py
unitprompt/matchers/uses/test_uses_html.py
unitprompt/matchers/uses/test_uses_latex.py
unitprompt/matchers/uses/test_uses_markdown.py
unitprompt/utils/get_prompt.py
unitprompt-0.0.9.dist-info/METADATA
unitprompt-0.0.9.dist-info/WHEEL
unitprompt-0.0.9.dist-info/RECORD
