Metadata-Version: 2.1
Name: unitprompt
Version: 0.0.9
Summary: A custom pytest matcher that helps you test prompts
Author: Jannis Conen
Author-email: jannis.conen@gmail.com
Requires-Python: >=3.10,<4.0
Classifier: Programming Language :: Python :: 3
Classifier: Programming Language :: Python :: 3.10
Classifier: Programming Language :: Python :: 3.11
Classifier: Programming Language :: Python :: 3.12
Requires-Dist: langchain (>=0.2.11,<0.3.0)
Requires-Dist: langchain-openai (>=0.1.19,<0.2.0)
Requires-Dist: pytest (>=8.3.2,<9.0.0)
Requires-Dist: pytest-asyncio (>=0.23.8,<0.24.0)
Requires-Dist: python-dotenv (>=1.0.1,<2.0.0)
Requires-Dist: pyyaml (>=6.0.1,<7.0.0)
